ShenduXuexiLilunYuShizhanTigaoPianFix1/README.md
ShenduXuexiLilunYuShizhanTigaoPianFix1/__init__.py
ShenduXuexiLilunYuShizhanTigaoPianFix1/__main__.py
ShenduXuexiLilunYuShizhanTigaoPianFix1/file.epub
ShenduXuexiLilunYuShizhanTigaoPianFix1/index.html
ShenduXuexiLilunYuShizhanTigaoPianFix1/css/__init__.py
ShenduXuexiLilunYuShizhanTigaoPianFix1/css/annotations.css
ShenduXuexiLilunYuShizhanTigaoPianFix1/css/main.css
ShenduXuexiLilunYuShizhanTigaoPianFix1/css/normalize.css
ShenduXuexiLilunYuShizhanTigaoPianFix1/css/popup.css
ShenduXuexiLilunYuShizhanTigaoPianFix1/font/__init__.py
ShenduXuexiLilunYuShizhanTigaoPianFix1/font/fontello.eot
ShenduXuexiLilunYuShizhanTigaoPianFix1/font/fontello.svg
ShenduXuexiLilunYuShizhanTigaoPianFix1/font/fontello.ttf
ShenduXuexiLilunYuShizhanTigaoPianFix1/font/fontello.woff
ShenduXuexiLilunYuShizhanTigaoPianFix1/img/__init__.py
ShenduXuexiLilunYuShizhanTigaoPianFix1/img/annotator-glyph-sprite.png
ShenduXuexiLilunYuShizhanTigaoPianFix1/img/annotator-icon-sprite.png
ShenduXuexiLilunYuShizhanTigaoPianFix1/img/apple-touch-icon.png
ShenduXuexiLilunYuShizhanTigaoPianFix1/img/cancelfullscreen.png
ShenduXuexiLilunYuShizhanTigaoPianFix1/img/close.png
ShenduXuexiLilunYuShizhanTigaoPianFix1/img/fullscreen.png
ShenduXuexiLilunYuShizhanTigaoPianFix1/img/loader.gif
ShenduXuexiLilunYuShizhanTigaoPianFix1/img/menu-icon.png
ShenduXuexiLilunYuShizhanTigaoPianFix1/img/save.png
ShenduXuexiLilunYuShizhanTigaoPianFix1/img/saved.png
ShenduXuexiLilunYuShizhanTigaoPianFix1/img/settings-s.png
ShenduXuexiLilunYuShizhanTigaoPianFix1/img/settings.png
ShenduXuexiLilunYuShizhanTigaoPianFix1/img/star.png
ShenduXuexiLilunYuShizhanTigaoPianFix1/js/__init__.py
ShenduXuexiLilunYuShizhanTigaoPianFix1/js/epub.js
ShenduXuexiLilunYuShizhanTigaoPianFix1/js/epub.min.js
ShenduXuexiLilunYuShizhanTigaoPianFix1/js/epub.min.map
ShenduXuexiLilunYuShizhanTigaoPianFix1/js/hooks.min.js
ShenduXuexiLilunYuShizhanTigaoPianFix1/js/hooks.min.map
shendu_xuexi_lilun_yu_shizhan_tigao_pian_fix1-2025.3.24.1.dist-info/METADATA
shendu_xuexi_lilun_yu_shizhan_tigao_pian_fix1-2025.3.24.1.dist-info/WHEEL
shendu_xuexi_lilun_yu_shizhan_tigao_pian_fix1-2025.3.24.1.dist-info/entry_points.txt
shendu_xuexi_lilun_yu_shizhan_tigao_pian_fix1-2025.3.24.1.dist-info/top_level.txt
shendu_xuexi_lilun_yu_shizhan_tigao_pian_fix1-2025.3.24.1.dist-info/RECORD
